firefly_integration/__init__.py
firefly_integration/application/__init__.py
firefly_integration/application/container.py
firefly_integration/application/service/__init__.py
firefly_integration/application/service/compact.py
firefly_integration/application/service/deduplicate_partitions.py
firefly_integration/application/service/filter_parquet.py
firefly_integration/application/service/load_data_catalogs.py
firefly_integration/application/service/map_reduce_functions.py
firefly_integration/application/service/query_data.py
firefly_integration/application/service/store_data.py
firefly_integration/domain/__init__.py
firefly_integration/domain/errors.py
firefly_integration/domain/data_catalog/__init__.py
firefly_integration/domain/data_catalog/catalog.py
firefly_integration/domain/data_catalog/catalog_registry.py
firefly_integration/domain/data_catalog/column.py
firefly_integration/domain/data_catalog/database.py
firefly_integration/domain/data_catalog/table.py
firefly_integration/domain/service/__init__.py
firefly_integration/domain/service/dal.py
firefly_integration/domain/service/marshal_dataframe.py
firefly_integration/domain/service/query_warehouse.py
firefly_integration/domain/service/remove_duplicates.py
firefly_integration/domain/service/sanitize_input_data.py
firefly_integration/domain/service/sql_parser.py
firefly_integration/domain/service/store_data.py
firefly_integration/domain/workflow/__init__.py
firefly_integration/domain/workflow/execute_workflow.py
firefly_integration/domain/workflow/function_parameters.py
firefly_integration/domain/workflow/function_registry.py
firefly_integration/domain/workflow/workflow.py
firefly_integration/domain/workflow/workflow_function.py
firefly_integration/infrastructure/__init__.py
firefly_integration/infrastructure/extensions/__init__.py
firefly_integration/infrastructure/extensions/aws_extension.py
firefly_integration/infrastructure/service/__init__.py
firefly_integration/infrastructure/service/dal/__init__.py
firefly_integration-1.0.41.dist-info/COPYING
firefly_integration-1.0.41.dist-info/METADATA
firefly_integration-1.0.41.dist-info/WHEEL
firefly_integration-1.0.41.dist-info/top_level.txt
firefly_integration-1.0.41.dist-info/RECORD
